LICENSE.txt
MANIFEST.in
README.rst
setup.cfg
setup.py
datakick/__init__.py
datakick/api.py
datakick/exceptions.py
datakick/models.py
datakick.egg-info/PKG-INFO
datakick.egg-info/SOURCES.txt
datakick.egg-info/dependency_links.txt
datakick.egg-info/requires.txt
datakick.egg-info/top_level.txt