Metadata-Version: 1.1
Name: datakick
Version: 0.0.1
Summary: UNKNOWN
Home-page: https://github.com/carlos-a-rodriguez/datakick
Author: Carlos A. Rodriguez
Author-email: carlos.rodriguez@protonmail.ch
License: MIT
Keywords: datakick barcode upc ean product
Platform: UNKNOWN
Classifier: Development Status :: 3 - Alpha
Classifier: Intended Audience :: Developers
Classifier: Topic :: Software Development :: Libraries :: Python Modules
Classifier: License :: OSI Approved :: MIT License
Classifier: Programming Language :: Python :: 2.7
Classifier: Programming Language :: Python :: 3.2
Classifier: Programming Language :: Python :: 3.3
Classifier: Programming Language :: Python :: 3.4
Classifier: Programming Language :: Python :: 3.5
